dbus_player_status/__init__.py
dbus_player_status/main.py
dbus_player_status-0.1.0.dist-info/entry_points.txt
dbus_player_status-0.1.0.dist-info/LICENSE
dbus_player_status-0.1.0.dist-info/WHEEL
dbus_player_status-0.1.0.dist-info/METADATA
dbus_player_status-0.1.0.dist-info/RECORD
