Metadata-Version: 2.1
Name: dbus-player-status
Version: 0.1.0
Summary: Tool to extract media player status via DBus in JSON format
License: BSD
Author: Tom Evans
Author-email: tevans.uk@googlemail.com
Requires-Python: >=3.8,<4.0
Classifier: License :: Other/Proprietary License
Classifier: Programming Language :: Python :: 3
Classifier: Programming Language :: Python :: 3.10
Classifier: Programming Language :: Python :: 3.8
Classifier: Programming Language :: Python :: 3.9
Requires-Dist: dbus-python (>=1.2.18,<2.0.0)
